shakenfist/agentoperation.py
shakenfist/artifact.py
shakenfist/baseobject.py
shakenfist/baseobjectmapping.py
shakenfist/blob.py
shakenfist/cache.py
shakenfist/config.py
shakenfist/constants.py
shakenfist/db.py
shakenfist/dhcp.py
shakenfist/etcd.py
shakenfist/eventlog.py
shakenfist/exceptions.py
shakenfist/images.py
shakenfist/instance.py
shakenfist/ipmanager.py
shakenfist/namespace.py
shakenfist/network.py
shakenfist/networkinterface.py
shakenfist/node.py
shakenfist/scheduler.py
shakenfist/tasks.py
shakenfist/upload.py
shakenfist/client/__init__.py
shakenfist/client/backup.py
shakenfist/client/ctl.py
shakenfist/daemons/checksums.py
shakenfist/daemons/cleaner.py
shakenfist/daemons/cluster.py
shakenfist/daemons/daemon.py
shakenfist/daemons/eventlog.py
shakenfist/daemons/external_api.py
shakenfist/daemons/main.py
shakenfist/daemons/net.py
shakenfist/daemons/queues.py
shakenfist/daemons/resources.py
shakenfist/daemons/shim.py
shakenfist/daemons/sidechannel.py
shakenfist/daemons/transfers.py
shakenfist/external_api/__init__.py
shakenfist/external_api/admin.py
shakenfist/external_api/agentoperation.py
shakenfist/external_api/app.py
shakenfist/external_api/artifact.py
shakenfist/external_api/auth.py
shakenfist/external_api/base.py
shakenfist/external_api/blob.py
shakenfist/external_api/instance.py
shakenfist/external_api/interface.py
shakenfist/external_api/label.py
shakenfist/external_api/network.py
shakenfist/external_api/node.py
shakenfist/external_api/snapshot.py
shakenfist/external_api/upload.py
shakenfist/external_api/util.py
shakenfist/tests/__init__.py
shakenfist/tests/base.py
shakenfist/tests/mock_etcd.py
shakenfist/tests/test_baseobject.py
shakenfist/tests/test_config.py
shakenfist/tests/test_daemon_cleaner.py
shakenfist/tests/test_dhcp.py
shakenfist/tests/test_etcd.py
shakenfist/tests/test_external_api.py
shakenfist/tests/test_images.py
shakenfist/tests/test_instance.py
shakenfist/tests/test_ipmanager.py
shakenfist/tests/test_net.py
shakenfist-0.7.2.dist-info/AUTHORS
shakenfist-0.7.2.dist-info/LICENSE
shakenfist-0.7.2.dist-info/METADATA
shakenfist-0.7.2.dist-info/WHEEL
shakenfist-0.7.2.dist-info/entry_points.txt
shakenfist-0.7.2.dist-info/pbr.json
shakenfist-0.7.2.dist-info/top_level.txt
shakenfist-0.7.2.dist-info/RECORD
